streamlit_pdf_viewer/__init__.py
streamlit_pdf_viewer/frontend/dist/index.html
streamlit_pdf_viewer/frontend/dist/css/app.1df382f3.css
streamlit_pdf_viewer/frontend/dist/css/chunk-vendors.ee6905b7.css
streamlit_pdf_viewer/frontend/dist/img/altText_add.7748ee93.svg
streamlit_pdf_viewer/frontend/dist/img/altText_done.1026be11.svg
streamlit_pdf_viewer/frontend/dist/img/cursor-editorFreeHighlight.1fed7bb7.svg
streamlit_pdf_viewer/frontend/dist/img/cursor-editorFreeText.0b596377.svg
streamlit_pdf_viewer/frontend/dist/img/cursor-editorInk.f94c2f42.svg
streamlit_pdf_viewer/frontend/dist/img/cursor-editorTextHighlight.5636640c.svg
streamlit_pdf_viewer/frontend/dist/img/editor-toolbar-delete.6694a89f.svg
streamlit_pdf_viewer/frontend/dist/img/toolbarButton-editorHighlight.c3287eaa.svg
streamlit_pdf_viewer/frontend/dist/img/toolbarButton-menuArrow.37a6145d.svg
streamlit_pdf_viewer/frontend/dist/js/app.0f29f50d.js
streamlit_pdf_viewer/frontend/dist/js/app.0f29f50d.js.map
streamlit_pdf_viewer/frontend/dist/js/chunk-vendors.a8702de6.js
streamlit_pdf_viewer/frontend/dist/js/chunk-vendors.a8702de6.js.map
tests/__init__.py
tests/e2e_utils.py
tests/test_embed_height.py
tests/test_embed_no_args.py
tests/test_embed_width.py
tests/test_embed_width_height.py
tests/test_iframe_height.py
tests/test_iframe_no_args.py
tests/test_iframe_width.py
tests/test_iframe_width_height.py
tests/test_invalid_params.py
tests/test_rendering_text.py
tests/test_resolution_boost.py
tests/test_tabs.py
tests/test_tabs_2.py
tests/test_unwrap_height.py
tests/test_unwrap_no_args.py
tests/test_unwrap_width.py
tests/test_unwrap_width_height.py
streamlit_pdf_viewer-0.0.25.dist-info/METADATA
streamlit_pdf_viewer-0.0.25.dist-info/WHEEL
streamlit_pdf_viewer-0.0.25.dist-info/top_level.txt
streamlit_pdf_viewer-0.0.25.dist-info/RECORD
