Metadata-Version: 2.4
Name: streamlit-pdf-viewer
Version: 0.0.25
Summary: Streamlit component for PDF visualisation and manipulation
Home-page: https://github.com/lfoppiano/streamlit-pdf-viewer
Author: Luca Foppiano, Tomoya Mato
Author-email: lucanoro@duck.com, tomoya.matou@gmail.com
Requires-Python: >=3.7
Requires-Dist: streamlit>=0.63
Provides-Extra: devel
Requires-Dist: wheel; extra == "devel"
Dynamic: author
Dynamic: author-email
Dynamic: description
Dynamic: description-content-type
Dynamic: home-page
Dynamic: provides-extra
Dynamic: requires-dist
Dynamic: requires-python
Dynamic: summary
